<?xml version="1.0" encoding="UTF-8"?>
<!DOCTYPE mapper PUBLIC "-//mybatis.org//DTD Mapper 3.0//EN" "http://mybatis.org/dtd/mybatis-3-mapper.dtd">
<mapper namespace="dam.jsoup.updatereport.updatreport.robot.dto.QqGroupDao">
  <resultMap id="BaseResultMap" type="dam.jsoup.updatereport.updatreport.robot.dto.QqGroup">
    <id column="id" jdbcType="INTEGER" property="id" />
    <result column="group_id" jdbcType="INTEGER" property="groupId" />
    <result column="group_name" jdbcType="VARCHAR" property="groupName" />
  </resultMap>
  <sql id="Example_Where_Clause">
    <where>
      <foreach collection="oredCriteria" item="criteria" separator="or">
        <if test="criteria.valid">
          <trim prefix="(" prefixOverrides="and" suffix=")">
            <foreach collection="criteria.criteria" item="criterion">
              <choose>
                <when test="criterion.noValue">
                  and ${criterion.condition}
                </when>
                <when test="criterion.singleValue">
                  and ${criterion.condition} #{criterion.value}
                </when>
                <when test="criterion.betweenValue">
                  and ${criterion.condition} #{criterion.value} and #{criterion.secondValue}
                </when>
                <when test="criterion.listValue">
                  and ${criterion.condition}
                  <foreach close=")" collection="criterion.value" item="listItem" open="(" separator=",">
                    #{listItem}
                  </foreach>
                </when>
              </choose>
            </foreach>
          </trim>
        </if>
      </foreach>
    </where>
  </sql>
  <sql id="Update_By_Example_Where_Clause">
    <where>
      <foreach collection="example.oredCriteria" item="criteria" separator="or">
        <if test="criteria.valid">
          <trim prefix="(" prefixOverrides="and" suffix=")">
            <foreach collection="criteria.criteria" item="criterion">
              <choose>
                <when test="criterion.noValue">
                  and ${criterion.condition}
                </when>
                <when test="criterion.singleValue">
                  and ${criterion.condition} #{criterion.value}
                </when>
                <when test="criterion.betweenValue">
                  and ${criterion.condition} #{criterion.value} and #{criterion.secondValue}
                </when>
                <when test="criterion.listValue">
                  and ${criterion.condition}
                  <foreach close=")" collection="criterion.value" item="listItem" open="(" separator=",">
                    #{listItem}
                  </foreach>
                </when>
              </choose>
            </foreach>
          </trim>
        </if>
      </foreach>
    </where>
  </sql>
  <sql id="Base_Column_List">
    id, group_id, group_name
  </sql>
  <select id="selectByExample" parameterType="dam.jsoup.updatereport.updatreport.robot.dto.QqGroupExample" resultMap="BaseResultMap">
    select
    <if test="distinct">
      distinct
    </if>
    <include refid="Base_Column_List" />
    from qq_group
    <if test="_parameter != null">
      <include refid="Example_Where_Clause" />
    </if>
    <if test="orderByClause != null">
      order by ${orderByClause}
    </if>
  </select>
  <select id="selectByPrimaryKey" parameterType="java.lang.Integer" resultMap="BaseResultMap">
    select 
    <include refid="Base_Column_List" />
    from qq_group
    where id = #{id,jdbcType=INTEGER}
  </select>
  <delete id="deleteByPrimaryKey" parameterType="java.lang.Integer">
    delete from qq_group
    where id = #{id,jdbcType=INTEGER}
  </delete>
  <delete id="deleteByExample" parameterType="dam.jsoup.updatereport.updatreport.robot.dto.QqGroupExample">
    delete from qq_group
    <if test="_parameter != null">
      <include refid="Example_Where_Clause" />
    </if>
  </delete>
  <insert id="insert" keyColumn="id" keyProperty="id" parameterType="dam.jsoup.updatereport.updatreport.robot.dto.QqGroup" useGeneratedKeys="true">
    insert into qq_group (group_id, group_name)
    values (#{groupId,jdbcType=INTEGER}, #{groupName,jdbcType=VARCHAR})
  </insert>
  <insert id="insertSelective" keyColumn="id" keyProperty="id" parameterType="dam.jsoup.updatereport.updatreport.robot.dto.QqGroup" useGeneratedKeys="true">
    insert into qq_group
    <trim prefix="(" suffix=")" suffixOverrides=",">
      <if test="groupId != null">
        group_id,
      </if>
      <if test="groupName != null">
        group_name,
      </if>
    </trim>
    <trim prefix="values (" suffix=")" suffixOverrides=",">
      <if test="groupId != null">
        #{groupId,jdbcType=INTEGER},
      </if>
      <if test="groupName != null">
        #{groupName,jdbcType=VARCHAR},
      </if>
    </trim>
  </insert>
  <select id="countByExample" parameterType="dam.jsoup.updatereport.updatreport.robot.dto.QqGroupExample" resultType="java.lang.Long">
    select count(*) from qq_group
    <if test="_parameter != null">
      <include refid="Example_Where_Clause" />
    </if>
  </select>
  <update id="updateByExampleSelective" parameterType="map">
    update qq_group
    <set>
      <if test="record.id != null">
        id = #{record.id,jdbcType=INTEGER},
      </if>
      <if test="record.groupId != null">
        group_id = #{record.groupId,jdbcType=INTEGER},
      </if>
      <if test="record.groupName != null">
        group_name = #{record.groupName,jdbcType=VARCHAR},
      </if>
    </set>
    <if test="_parameter != null">
      <include refid="Update_By_Example_Where_Clause" />
    </if>
  </update>
  <update id="updateByExample" parameterType="map">
    update qq_group
    set id = #{record.id,jdbcType=INTEGER},
      group_id = #{record.groupId,jdbcType=INTEGER},
      group_name = #{record.groupName,jdbcType=VARCHAR}
    <if test="_parameter != null">
      <include refid="Update_By_Example_Where_Clause" />
    </if>
  </update>
  <update id="updateByPrimaryKeySelective" parameterType="dam.jsoup.updatereport.updatreport.robot.dto.QqGroup">
    update qq_group
    <set>
      <if test="groupId != null">
        group_id = #{groupId,jdbcType=INTEGER},
      </if>
      <if test="groupName != null">
        group_name = #{groupName,jdbcType=VARCHAR},
      </if>
    </set>
    where id = #{id,jdbcType=INTEGER}
  </update>
  <update id="updateByPrimaryKey" parameterType="dam.jsoup.updatereport.updatreport.robot.dto.QqGroup">
    update qq_group
    set group_id = #{groupId,jdbcType=INTEGER},
      group_name = #{groupName,jdbcType=VARCHAR}
    where id = #{id,jdbcType=INTEGER}
  </update>
</mapper>